Metadata-Version: 2.1
Name: aamarpay
Version: 1.0.1
Summary: Payment gateway libarary
Home-page: https://github.com/sanjidbillah/aamarPay-python
Author: Masum billah sanjid
Author-email: masumbillahsanjid@gmail.com
License: MIT
Keywords: aamarPay payment gateway python
Platform: UNKNOWN
Classifier: Development Status :: 5 - Production/Stable
Classifier: Intended Audience :: Education
Classifier: Operating System :: Microsoft :: Windows :: Windows 10
Classifier: License :: OSI Approved :: MIT License
Classifier: Programming Language :: Python :: 3
